PartI/fsm_moore2.v
module fsm(clk, rst, inp, outp); 

input clk,rst,inp;
output reg outp;
localparam S0 = 3'b000;
localparam S1 = 3'b001;
localparam S2 = 3'b010;
localparam S3 = 3'b011;
localparam S4 = 3'b100;
reg [2:0] state;

always @(posedge clk, posedge rst)
begin
    if(rst)
        state <= S0;
    else
    begin
    case (state)
    S0:
        begin
            if(inp) state <= S1;
            else state <= S0;
        end
    S1:
        begin
            if(inp) state <= S1;
            else state <= S2;
        end
    S2:
        begin
            if(inp) state <= S3;
            else state <= S0;
        end
    S3:
        begin
            if(inp) state <= S4;
            else state <= S2;
        end
    S4:
        begin
            if(inp) state <= S1;
            else state <= S2;
        end
    endcase
    end
end

always @(posedge clk, posedge rst)
begin
    if (rst) 
    outp <= 0;
    else if(state==S4)
    outp <=1;
    else 
    outp <=0;
end

endmodule

PartI/fsm_test2.v
module fsm_test2;

reg  clk, rst, inp;
wire outp;
reg[31:0] sequence;
integer i;

fsm dut( clk, rst, inp, outp);

initial
begin

   clk = 0;
        rst = 1;
        sequence = 32'b0101_0111_0111_0010_0100_1111_0110_1011;
   #5 rst = 0;

   for( i = 0; i <= 31; i = i + 1)
   begin
      inp = sequence[i];
      #2 clk = 1;
      #2 clk = 0;
      $display("State = ", dut.state, " Input = ", inp, ", Output = ", outp);

   end
end

initial
begin
$dumpfile("test.vcd");
$dumpvars(0,fsm_test2);  
end

endmodule

PartI/test.vcd
$date
	Thu Nov 19 20:29:15 2020
$end
$version
	Icarus Verilog
$end
$timescale
	1s
$end
$scope module fsm_test2 $end
$var wire 1 ! outp $end
$var reg 1 " clk $end
$var reg 1 # inp $end
$var reg 1 $ rst $end
$var reg 32 % sequence [31:0] $end
$var integer 32 & i [31:0] $end
$scope module dut $end
$var wire 1 " clk $end
$var wire 1 # inp $end
$var wire 1 $ rst $end
$var reg 1 ! outp $end
$var reg 3 ' state [2:0] $end
$upscope $end
$upscope $end
$enddefinitions $end
#0
$dumpvars
b0 '
bx &
b1010111011100100100111101101011 %
1$
x#
0"
0!
$end
#5
1#
b0 &
0$
#7
b1 '
1"
#9
b1 &
0"
#11
1"
#13
0#
b10 &
0"
#15
b10 '
1"
#17
1#
b11 &
0"
#19
b11 '
1"
#21
0#
b100 &
0"
#23
b10 '
1"
#25
1#
b101 &
0"
#27
b11 '
1"
#29
b110 &
0"
#31
b100 '
1"
#33
0#
b111 &
0"
#35
b10 '
1!
1"
#37
1#
b1000 &
0"
#39
0!
b11 '
1"
#41
b1001 &
0"
#43
b100 '
1"
#45
b1010 &
0"
#47
1!
b1 '
1"
#49
b1011 &
0"
#51
0!
1"
#53
0#
b1100 &
0"
#55
b10 '
1"
#57
b1101 &
0"
#59
b0 '
1"
#61
1#
b1110 &
0"
#63
b1 '
1"
#65
0#
b1111 &
0"
#67
b10 '
1"
#69
b10000 &
0"
#71
b0 '
1"
#73
1#
b10001 &
0"
#75
b1 '
1"
#77
0#
b10010 &
0"
#79
b10 '
1"
#81
b10011 &
0"
#83
b0 '
1"
#85
1#
b10100 &
0"
#87
b1 '
1"
#89
b10101 &
0"
#91
1"
#93
b10110 &
0"
#95
1"
#97
0#
b10111 &
0"
#99
b10 '
1"
#101
1#
b11000 &
0"
#103
b11 '
1"
#105
b11001 &
0"
#107
b100 '
1"
#109
b11010 &
0"
#111
1!
b1 '
1"
#113
0#
b11011 &
0"
#115
b10 '
0!
1"
#117
1#
b11100 &
0"
#119
b11 '
1"
#121
0#
b11101 &
0"
#123
b10 '
1"
#125
1#
b11110 &
0"
#127
b11 '
1"
#129
0#
b11111 &
0"
#131
b10 '
1"
#133
b100000 &
0"
