PartI/fsm_moore2.v
module fsm(clk, rst, inp, outp); 

input clk,rst,inp;
output reg outp;
localparam S0 = 3'b000;
localparam S1 = 3'b001;
localparam S2 = 3'b010;
localparam S3 = 3'b011;
localparam S4 = 3'b100;
reg [2:0] state;

always @(posedge clk, posedge rst)
begin
    if(rst)
        state <= S0;
    else
    begin
    case (state)
    S0:
        begin
            if(inp) state <= S1;
            else state <= S0;
        end
    S1:
        begin
            if(inp) state <= S1;
            else state <= S2;
        end
    S2:
        begin
            if(inp) state <= S3;
            else state <= S0;
        end
    S3:
        begin
            if(inp) state <= S4;
            else state <= S2;
        end
    S4:
        begin
            if(inp) state <= S1;
            else state <= S2;
        end
    endcase
    end
end

always @(posedge clk, posedge rst)
begin
    if (rst) 
    outp <= 0;
    else if(state==S4)
    outp <=1;
    else 
    outp <=0;
end

endmodule

PartI/fsm_test.v
module fsm_test;

reg  clk, rst, inp;
wire outp;
reg[15:0] sequence;
integer i;

//fsm_moore dut( clk, rst, inp, outp);
fsm dut(clk,rst,inp,outp);
initial
begin

   clk = 0;
        rst = 1;
        sequence = 16'b0101_0111_0111_0010;
   #5 rst = 0;

   for( i = 0; i <= 15; i = i + 1)
   begin
      inp = sequence[i];
      #2 clk = 1;
      #2 clk = 0;
      $display("State = ", dut.state, " Input = ", inp, ", Output = ", outp);

   end
        test2;
end
task test2;
   for( i = 0; i <= 15; i = i + 1)
   begin
      inp = $random % 2;
      #2 clk = 1;
      #2 clk = 0;
      $display("State = ", dut.state, " Input = ", inp, ", Output = ", outp);

   end
endtask
initial
begin
$dumpfile("test.vcd");
$dumpvars(0,fsm_test);  
end

endmodule

PartI/test.vcd
$date
	Thu Nov 19 20:24:33 2020
$end
$version
	Icarus Verilog
$end
$timescale
	1s
$end
$scope module fsm_test $end
$var wire 1 ! outp $end
$var reg 1 " clk $end
$var reg 1 # inp $end
$var reg 1 $ rst $end
$var reg 16 % sequence [15:0] $end
$var integer 32 & i [31:0] $end
$scope module dut $end
$var wire 1 " clk $end
$var wire 1 # inp $end
$var wire 1 $ rst $end
$var reg 1 ! outp $end
$var reg 3 ' state [2:0] $end
$upscope $end
$scope task test2 $end
$upscope $end
$upscope $end
$enddefinitions $end
#0
$dumpvars
b0 '
bx &
b101011101110010 %
1$
x#
0"
0!
$end
#5
0#
b0 &
0$
#7
1"
#9
1#
b1 &
0"
#11
b1 '
1"
#13
0#
b10 &
0"
#15
b10 '
1"
#17
b11 &
0"
#19
b0 '
1"
#21
1#
b100 &
0"
#23
b1 '
1"
#25
b101 &
0"
#27
1"
#29
b110 &
0"
#31
1"
#33
0#
b111 &
0"
#35
b10 '
1"
#37
1#
b1000 &
0"
#39
b11 '
1"
#41
b1001 &
0"
#43
b100 '
1"
#45
b1010 &
0"
#47
1!
b1 '
1"
#49
0#
b1011 &
0"
#51
b10 '
0!
1"
#53
1#
b1100 &
0"
#55
b11 '
1"
#57
0#
b1101 &
0"
#59
b10 '
1"
#61
1#
b1110 &
0"
#63
b11 '
1"
#65
0#
b1111 &
0"
#67
b10 '
1"
#69
b0 &
0"
#71
b0 '
1"
#73
1#
b1 &
0"
#75
b1 '
1"
#77
b10 &
0"
#79
1"
#81
b11 &
0"
#83
1"
#85
b100 &
0"
#87
1"
#89
b101 &
0"
#91
1"
#93
b110 &
0"
#95
1"
#97
0#
b111 &
0"
#99
b10 '
1"
#101
1#
b1000 &
0"
#103
b11 '
1"
#105
b1001 &
0"
#107
b100 '
1"
#109
0#
b1010 &
0"
#111
1!
b10 '
1"
#113
1#
b1011 &
0"
#115
b11 '
0!
1"
#117
b1100 &
0"
#119
b100 '
1"
#121
0#
b1101 &
0"
#123
b10 '
1!
1"
#125
1#
b1110 &
0"
#127
0!
b11 '
1"
#129
0#
b1111 &
0"
#131
b10 '
1"
#133
b10000 &
0"
